bclearer_interop_services/__init__.py
bclearer_interop_services/b_dictionary_service.url
bclearer_interop_services/file_system_snapshot_universe_service.url
bclearer_interop_services/b_dictionary_service/__init__.py
bclearer_interop_services/b_dictionary_service/dataframe_to_table_b_dictionary_converter.py
bclearer_interop_services/b_dictionary_service/table_b_dictionary_by_table_names_getter.py
bclearer_interop_services/b_dictionary_service/table_b_dictionary_column_renamer.py
bclearer_interop_services/b_dictionary_service/table_b_dictionary_column_reorderer.py
bclearer_interop_services/b_dictionary_service/table_b_dictionary_column_with_constant_value_adder.py
bclearer_interop_services/b_dictionary_service/table_b_dictionary_to_dataframe_converter.py
bclearer_interop_services/b_dictionary_service/table_b_dictionary_to_networkx_edges_dictionary_converter.py
bclearer_interop_services/b_dictionary_service/table_b_dictionary_to_networkx_node_attributes_list_converter.py
bclearer_interop_services/b_dictionary_service/common_knowledge/__init__.py
bclearer_interop_services/b_dictionary_service/common_knowledge/b_dictionary_return_types.py
bclearer_interop_services/b_dictionary_service/common_knowledge/table_b_dictionary_return_types.py
bclearer_interop_services/b_dictionary_service/common_knowledge/table_register_b_dictionary_return_types.py
bclearer_interop_services/b_dictionary_service/mapper_objects_service/__init__.py
bclearer_interop_services/b_dictionary_service/mapper_objects_service/mapper_objects_to_table_converter.py
bclearer_interop_services/b_dictionary_service/objects/__init__.py
bclearer_interop_services/b_dictionary_service/objects/b_dictionaries.py
bclearer_interop_services/b_dictionary_service/objects/row_b_dictionaries.py
bclearer_interop_services/b_dictionary_service/objects/table_b_dictionaries.py
bclearer_interop_services/b_dictionary_service/objects/table_registers.py
bclearer_interop_services-0.6.0.dist-info/METADATA
bclearer_interop_services-0.6.0.dist-info/WHEEL
bclearer_interop_services-0.6.0.dist-info/licenses/LICENSE.md
bclearer_interop_services-0.6.0.dist-info/RECORD
