Metadata-Version: 2.4
Name: bclearer-interop-services
Version: 0.6.0
Summary: "A set of interop services to integrate and transfer data between different applications, model and storage technologies for the bclearer framework."
Author-email: Mesbah Khan <khanm@ontoledgy.io>
License-File: LICENSE.md
Requires-Python: >=3.12
Requires-Dist: bclearer-orchestration-services<0.3.0,>=0.2.8
Requires-Dist: cozo-embedded==0.7.6
Requires-Dist: pycozo==0.7.6
Provides-Extra: yxdb
Requires-Dist: yxdb>=1.1.1; extra == 'yxdb'
